rsled_api/__init__.py
rsled_api/const.py
rsled_api/interpolate.py
rsled_api/rsled_api.py
rsled_api/utility.py
rsled_api-1.0.0.dist-info/LICENSE
rsled_api-1.0.0.dist-info/METADATA
rsled_api-1.0.0.dist-info/WHEEL
rsled_api-1.0.0.dist-info/top_level.txt
rsled_api-1.0.0.dist-info/RECORD
