Metadata-Version: 2.1
Name: rsled_api
Version: 1.0.0
Summary: Python API for Red Sea ReefLED lights
Author-email: Bretton Wade <bretton.wade@gmail.com>
Maintainer-email: Bretton Wade <bretton.wade@gmail.com>
License: MIT License
Project-URL: Homepage, https://github.com/brettonw/RSLED
Keywords: home assistant,red sea,rsled,reefled
Classifier: Programming Language :: Python
Classifier: Programming Language :: Python :: 3
Requires-Python: >=3.9
License-File: LICENSE
Provides-Extra: dev
Requires-Dist: pytest; extra == "dev"
